[{"name":"render_template.action_view","payload":{"identifier":"/Users/jamiewallace/Development/sourdough_app_v2/app/views/welcome/forum.html.haml","layout":"layouts/application"},"time":"2014-01-31T23:59:58+00:00","transaction_id":"55b5fbaa451ab9b3c13e","end":"2014-01-31T23:59:58+00:00","duration":3.1879999999999997},{"name":"process_action.action_controller","payload":{"controller":"WelcomeController","action":"forum","params":{"controller":"welcome","action":"forum"},"format":"html","method":"GET","path":"/forum","status":200,"view_runtime":95.553,"db_runtime":0},"time":"2014-01-31T23:59:57+00:00","transaction_id":"55b5fbaa451ab9b3c13e","end":"2014-01-31T23:59:58+00:00","duration":95.914}]