[{"name":"sql.active_record","payload":{"sql":"SELECT  \"users\".* FROM \"users\"  WHERE \"users\".\"email\" = 'wallacejamiec@gmail.com' LIMIT 1","name":"User Load","connection_id":70119195077840,"binds":[]},"time":"2014-01-22T11:32:23+00:00","transaction_id":"355b65ab94bc8d1c9a2f","end":"2014-01-22T11:32:23+00:00","duration":7.89},{"name":"sql.active_record","payload":{"sql":"BEGIN","name":null,"connection_id":70119195077840,"binds":[]},"time":"2014-01-22T11:32:23+00:00","transaction_id":"355b65ab94bc8d1c9a2f","end":"2014-01-22T11:32:23+00:00","duration":0.13999999999999999},{"name":"sql.active_record","payload":{"sql":"UPDATE \"users\" SET \"last_sign_in_at\" = '2014-01-22 11:32:23.448625', \"current_sign_in_at\" = '2014-01-22 11:32:23.448625', \"last_sign_in_ip\" = '127.0.0.1', \"current_sign_in_ip\" = '127.0.0.1', \"sign_in_count\" = 1, \"updated_at\" = '2014-01-22 11:32:23.451108' WHERE \"users\".\"id\" = 2","name":null,"connection_id":70119195077840,"binds":[]},"time":"2014-01-22T11:32:23+00:00","transaction_id":"355b65ab94bc8d1c9a2f","end":"2014-01-22T11:32:23+00:00","duration":26.807000000000002},{"name":"sql.active_record","payload":{"sql":"COMMIT","name":null,"connection_id":70119195077840,"binds":[]},"time":"2014-01-22T11:32:23+00:00","transaction_id":"355b65ab94bc8d1c9a2f","end":"2014-01-22T11:32:23+00:00","duration":1.553},{"name":"sql.active_record","payload":{"sql":"SELECT  \"users\".* FROM \"users\"  WHERE \"users\".\"id\" = $1 LIMIT 1","name":"User Load","connection_id":70119195077840,"binds":[[{"name":"id","sql_type":"integer","null":false,"limit":null,"precision":null,"scale":null,"type":"integer","default":null,"primary":true,"coder":null},"2"]]},"time":"2014-01-22T11:32:23+00:00","transaction_id":"355b65ab94bc8d1c9a2f","end":"2014-01-22T11:32:23+00:00","duration":0.40499999999999997},{"name":"process_action.action_controller","payload":{"controller":"SessionsController","action":"create","params":{"utf8":"\u2713","authenticity_token":"MqKZxvnyOyKrvAqX4mwbL7z3MWkzgg96lXoaFd9qIvY=","user":{"email":"wallacejamiec@gmail.com","password":"[FILTERED]","remember_me":"0"},"ref_user_id":"2","commit":"Sign in","action":"create","controller":"sessions"},"format":"html","method":"POST","path":"/users/sign_in","status":302,"view_runtime":null,"db_runtime":36.795},"time":"2014-01-22T11:32:23+00:00","transaction_id":"38d7b7ef9a8f2000a4ad","end":"2014-01-22T11:32:23+00:00","duration":134.564}]